{"tt0159876":[{"r":9.3,"s":15,"e":2},{"r":9.3,"s":26,"e":11},{"r":9.2,"s":24,"e":10},{"r":9.1,"s":13,"e":10},{"r":9.1,"s":23,"e":12}],"tt0159920":[{"r":7.3,"s":1,"e":3},{"r":7.2,"s":1,"e":2},{"r":6.9,"s":1,"e":6},{"r":6.8,"s":1,"e":5},{"r":6.8,"s":1,"e":4}],"tt0159386":[{"r":8.1,"s":1,"e":1},{"r":6.8,"s":1,"e":6},{"r":6.7,"s":1,"e":2},{"r":6.6,"s":1,"e":3},{"r":6.4,"s":1,"e":4}],"tt0159156":[{"r":8.8,"s":4,"e":25},{"r":8.3,"s":9,"e":3},{"r":8.0,"s":2,"e":14},{"r":8.0,"s":2,"e":9},{"r":6.8,"s":2,"e":36}],"tt0155428":[{"r":9.7,"s":3,"e":49},{"r":2.1,"s":1,"e":35}],"tt0154061":[{"r":7.4,"s":1,"e":3},{"r":7.3,"s":3,"e":2},{"r":7.3,"s":1,"e":10},{"r":7.2,"s":1,"e":15},{"r":7.1,"s":1,"e":14}],"tt0155425":[{"r":5.6,"s":1,"e":1},{"r":5.3,"s":1,"e":2}],"tt0157218":[{"r":6.0,"s":1,"e":1}],"tt0158552":[{"r":9.2,"s":8,"e":22},{"r":9.1,"s":3,"e":22},{"r":8.8,"s":1,"e":22},{"r":8.8,"s":1,"e":17},{"r":8.7,"s":5,"e":12}],"tt0156442":[{"r":8.5,"s":1,"e":2},{"r":8.5,"s":1,"e":3},{"r":8.2,"s":1,"e":1},{"r":8.0,"s":1,"e":4}],"tt0158411":[{"r":8.3,"s":1,"e":24},{"r":8.2,"s":1,"e":22},{"r":8.1,"s":1,"e":19},{"r":8.0,"s":1,"e":5},{"r":7.9,"s":1,"e":16}],"tt0159875":[{"r":8.5,"s":1,"e":4},{"r":8.1,"s":1,"e":11},{"r":7.8,"s":1,"e":5},{"r":7.6,"s":1,"e":2},{"r":7.5,"s":1,"e":1}],"tt0156214":[{"r":7.6,"s":1,"e":1},{"r":7.3,"s":1,"e":3},{"r":7.2,"s":1,"e":2},{"r":7.1,"s":1,"e":4}],"tt0159178":[{"r":8.2,"s":3,"e":6},{"r":7.9,"s":1,"e":9},{"r":7.8,"s":2,"e":10},{"r":7.7,"s":2,"e":3},{"r":7.7,"s":2,"e":4}],"tt0159192":[{"r":8.3,"s":4,"e":52},{"r":8.1,"s":4,"e":42},{"r":7.4,"s":2,"e":10},{"r":7.2,"s":1,"e":9},{"r":7.1,"s":1,"e":8}],"tt0159206":[{"r":8.8,"s":6,"e":20},{"r":8.3,"s":2,"e":18},{"r":8.2,"s":4,"e":18},{"r":8.2,"s":4,"e":8},{"r":8.2,"s":4,"e":2}],"tt0157246":[{"r":8.9,"s":6,"e":2},{"r":8.9,"s":9,"e":4},{"r":8.9,"s":9,"e":6},{"r":8.8,"s":3,"e":8},{"r":8.7,"s":4,"e":16}],"tt0158443":[{"r":5.6,"s":1,"e":1}],"tt0159175":[{"r":7.6,"s":1,"e":4},{"r":7.6,"s":1,"e":9},{"r":7.4,"s":1,"e":15},{"r":7.3,"s":1,"e":8},{"r":7.3,"s":1,"e":17}],"tt0159193":[{"r":9.0,"s":1,"e":49},{"r":8.7,"s":1,"e":7},{"r":8.7,"s":1,"e":24},{"r":8.7,"s":1,"e":44},{"r":8.3,"s":1,"e":10}],"tt0159172":[{"r":8.7,"s":1,"e":43},{"r":8.7,"s":1,"e":41},{"r":8.6,"s":1,"e":38},{"r":8.5,"s":1,"e":42},{"r":8.4,"s":1,"e":40}],"tt0156221":[{"r":6.2,"s":1,"e":3},{"r":6.2,"s":1,"e":13},{"r":6.1,"s":1,"e":1},{"r":6.0,"s":1,"e":4},{"r":5.9,"s":1,"e":11}],"tt0159208":[{"r":8.3,"s":1,"e":5},{"r":7.9,"s":1,"e":1},{"r":7.5,"s":1,"e":4},{"r":7.4,"s":1,"e":2},{"r":7.4,"s":1,"e":3}],"tt0159184":[{"r":9.5,"s":1,"e":36},{"r":7.4,"s":1,"e":2},{"r":6.7,"s":1,"e":1}],"tt0156200":[{"r":7.4,"s":1,"e":1}],"tt0158417":[{"r":8.4,"s":1,"e":66},{"r":8.2,"s":1,"e":65},{"r":7.9,"s":1,"e":67},{"r":7.8,"s":1,"e":57},{"r":7.8,"s":1,"e":63}],"tt0157217":[{"r":8.8,"s":1,"e":1},{"r":8.7,"s":1,"e":3},{"r":8.4,"s":1,"e":2}],"tt0159186":[{"r":9.4,"s":1,"e":49},{"r":9.3,"s":1,"e":36},{"r":9.2,"s":1,"e":50},{"r":9.1,"s":1,"e":46},{"r":9.1,"s":1,"e":37}],"tt0159567":[{"r":8.8,"s":1,"e":9}],"tt0159569":[{"r":9.1,"s":1,"e":10},{"r":8.9,"s":1,"e":11},{"r":8.6,"s":1,"e":6},{"r":8.5,"s":1,"e":7},{"r":8.4,"s":1,"e":9}],"tt0159145":[{"r":8.5,"s":1,"e":6},{"r":8.1,"s":1,"e":1},{"r":8.1,"s":1,"e":5},{"r":7.9,"s":1,"e":2},{"r":7.9,"s":1,"e":4}],"tt0158634":[{"r":6.9,"s":1,"e":1},{"r":6.8,"s":1,"e":3},{"r":6.8,"s":1,"e":2},{"r":6.4,"s":1,"e":4}],"tt0156205":[{"r":6.1,"s":1,"e":2},{"r":5.9,"s":1,"e":1}],"tt0158466":[{"r":8.1,"s":1,"e":1},{"r":8.0,"s":1,"e":2}]}