{"tt2626500":[{"r":8.8,"s":1,"e":2}],"tt2621722":[{"r":8.8,"s":1,"e":49},{"r":8.3,"s":1,"e":4},{"r":8.2,"s":1,"e":5},{"r":7.9,"s":1,"e":1},{"r":7.2,"s":1,"e":2}],"tt26246598":[{"r":6.7,"s":1,"e":3},{"r":6.7,"s":1,"e":5},{"r":6.7,"s":2,"e":3},{"r":6.6,"s":1,"e":4},{"r":6.4,"s":1,"e":6}],"tt2622982":[{"r":8.0,"s":1,"e":12},{"r":7.9,"s":1,"e":5},{"r":7.6,"s":1,"e":11},{"r":7.5,"s":1,"e":1},{"r":7.5,"s":1,"e":3}],"tt26225090":[{"r":9.1,"s":1,"e":11},{"r":8.9,"s":1,"e":12},{"r":8.7,"s":1,"e":6},{"r":8.6,"s":1,"e":4},{"r":8.6,"s":1,"e":7}],"tt26228426":[{"r":9.1,"s":1,"e":4},{"r":9.0,"s":1,"e":8},{"r":8.8,"s":1,"e":3},{"r":8.8,"s":1,"e":6},{"r":8.7,"s":1,"e":1}],"tt26229508":[{"r":8.8,"s":1,"e":10},{"r":8.7,"s":1,"e":6},{"r":8.6,"s":1,"e":9},{"r":8.6,"s":1,"e":8},{"r":8.4,"s":1,"e":7}],"tt26235088":[{"r":8.5,"s":1,"e":26},{"r":8.1,"s":1,"e":2},{"r":7.8,"s":1,"e":9},{"r":7.8,"s":1,"e":38},{"r":7.7,"s":1,"e":19}],"tt26218818":[{"r":9.0,"s":1,"e":6},{"r":8.5,"s":1,"e":5},{"r":8.2,"s":1,"e":1},{"r":8.2,"s":1,"e":4},{"r":8.0,"s":1,"e":2}],"tt26218826":[{"r":8.1,"s":1,"e":8},{"r":8.0,"s":1,"e":3},{"r":7.8,"s":1,"e":1},{"r":7.8,"s":1,"e":5},{"r":7.8,"s":1,"e":6}],"tt26239548":[{"r":5.0,"s":1,"e":1},{"r":4.5,"s":1,"e":2},{"r":4.1,"s":1,"e":3}],"tt26217696":[{"r":7.0,"s":1,"e":1},{"r":6.8,"s":1,"e":3},{"r":6.6,"s":1,"e":2}],"tt26253514":[{"r":8.6,"s":1,"e":12},{"r":8.4,"s":1,"e":8},{"r":8.4,"s":1,"e":9},{"r":8.3,"s":1,"e":2},{"r":8.3,"s":1,"e":16}],"tt26256066":[{"r":7.3,"s":1,"e":1}],"tt26256718":[{"r":5.9,"s":1,"e":24},{"r":5.6,"s":1,"e":6},{"r":5.5,"s":1,"e":7},{"r":5.3,"s":1,"e":1},{"r":5.2,"s":1,"e":8}],"tt26245850":[{"r":8.4,"s":1,"e":10},{"r":8.4,"s":2,"e":7},{"r":8.2,"s":1,"e":1},{"r":8.2,"s":1,"e":2},{"r":8.0,"s":2,"e":2}],"tt2622240":[{"r":7.0,"s":1,"e":1},{"r":7.0,"s":1,"e":3},{"r":6.7,"s":1,"e":2}],"tt2624808":[{"r":8.0,"s":1,"e":1},{"r":7.4,"s":1,"e":2}],"tt26270657":[{"r":7.7,"s":1,"e":1},{"r":7.7,"s":1,"e":4},{"r":7.5,"s":1,"e":3},{"r":7.2,"s":1,"e":8},{"r":7.0,"s":1,"e":5}],"tt26287941":[{"r":8.8,"s":1,"e":1}],"tt2626902":[{"r":8.2,"s":1,"e":2},{"r":8.0,"s":1,"e":1},{"r":8.0,"s":1,"e":3}],"tt2624370":[{"r":9.6,"s":3,"e":5},{"r":9.6,"s":3,"e":7},{"r":9.5,"s":3,"e":8},{"r":9.4,"s":2,"e":8},{"r":9.4,"s":1,"e":5}],"tt26250668":[{"r":8.8,"s":1,"e":3},{"r":8.4,"s":1,"e":1}],"tt26224444":[{"r":8.0,"s":2,"e":1},{"r":7.8,"s":1,"e":9},{"r":7.5,"s":1,"e":4},{"r":7.3,"s":1,"e":6},{"r":7.1,"s":1,"e":2}],"tt26218006":[{"r":10.0,"s":1,"e":4},{"r":9.7,"s":1,"e":3},{"r":9.4,"s":1,"e":2},{"r":9.1,"s":1,"e":1}],"tt2626138":[{"r":7.8,"s":1,"e":1},{"r":7.6,"s":1,"e":7},{"r":7.6,"s":1,"e":9},{"r":7.5,"s":1,"e":2},{"r":7.5,"s":1,"e":6}],"tt2626976":[{"r":9.4,"s":1,"e":2},{"r":9.2,"s":1,"e":1}],"tt26228446":[{"r":7.7,"s":1,"e":3},{"r":7.3,"s":1,"e":2},{"r":7.2,"s":2,"e":3},{"r":7.1,"s":1,"e":1},{"r":7.1,"s":2,"e":7}],"tt26241746":[{"r":7.0,"s":1,"e":10},{"r":6.8,"s":1,"e":1},{"r":6.7,"s":1,"e":9},{"r":6.4,"s":1,"e":8},{"r":6.2,"s":1,"e":2}],"tt26217706":[{"r":8.1,"s":1,"e":2},{"r":8.1,"s":1,"e":3},{"r":8.0,"s":1,"e":1},{"r":8.0,"s":1,"e":4},{"r":7.9,"s":1,"e":8}],"tt26258202":[{"r":5.4,"s":1,"e":6},{"r":5.4,"s":1,"e":9},{"r":5.3,"s":1,"e":1},{"r":5.3,"s":1,"e":12},{"r":5.3,"s":1,"e":3}],"tt26258200":[{"r":8.2,"s":1,"e":4},{"r":7.6,"s":1,"e":3},{"r":7.6,"s":1,"e":6},{"r":7.4,"s":1,"e":7},{"r":7.3,"s":1,"e":2}],"tt26259688":[{"r":7.3,"s":1,"e":2},{"r":6.9,"s":1,"e":1},{"r":6.9,"s":1,"e":4},{"r":6.8,"s":1,"e":8},{"r":6.7,"s":1,"e":3}],"tt26250926":[{"r":8.8,"s":1,"e":7},{"r":8.2,"s":1,"e":2},{"r":7.8,"s":1,"e":4},{"r":7.2,"s":1,"e":1}],"tt2625268":[{"r":6.6,"s":1,"e":3}],"tt26250592":[{"r":6.4,"s":1,"e":1}],"tt26259204":[{"r":6.6,"s":1,"e":1}],"tt26228312":[{"r":8.4,"s":1,"e":12},{"r":8.4,"s":1,"e":11},{"r":8.4,"s":1,"e":14},{"r":8.3,"s":1,"e":6},{"r":8.3,"s":1,"e":13}],"tt26243184":[{"r":8.3,"s":1,"e":1},{"r":7.5,"s":1,"e":5},{"r":7.0,"s":1,"e":2}],"tt26225038":[{"r":9.0,"s":1,"e":4},{"r":8.5,"s":1,"e":3},{"r":8.5,"s":1,"e":6},{"r":8.4,"s":1,"e":2},{"r":8.4,"s":1,"e":8}],"tt26249644":[{"r":9.5,"s":1,"e":11},{"r":8.1,"s":1,"e":1},{"r":8.0,"s":1,"e":2}],"tt26215550":[{"r":7.9,"s":1,"e":8},{"r":7.8,"s":1,"e":3},{"r":7.7,"s":1,"e":6},{"r":7.7,"s":1,"e":5},{"r":7.6,"s":1,"e":2}],"tt26246998":[{"r":9.9,"s":2,"e":17},{"r":9.9,"s":1,"e":15},{"r":9.5,"s":2,"e":7},{"r":9.5,"s":3,"e":9},{"r":9.4,"s":1,"e":1}],"tt26215854":[{"r":8.4,"s":1,"e":2},{"r":8.2,"s":1,"e":1},{"r":8.2,"s":1,"e":3},{"r":8.2,"s":1,"e":4}],"tt2629564":[{"r":7.5,"s":1,"e":1},{"r":7.4,"s":1,"e":3},{"r":7.3,"s":1,"e":2}],"tt26246248":[{"r":7.6,"s":1,"e":3},{"r":7.4,"s":1,"e":2},{"r":7.4,"s":1,"e":7},{"r":7.4,"s":1,"e":6},{"r":7.3,"s":1,"e":4}],"tt26226138":[{"r":9.3,"s":1,"e":1}],"tt26297744":[{"r":9.0,"s":1,"e":1}],"tt26217118":[{"r":8.0,"s":3,"e":3},{"r":7.6,"s":3,"e":1},{"r":7.6,"s":3,"e":2},{"r":7.6,"s":3,"e":9},{"r":7.5,"s":3,"e":5}],"tt2622990":[{"r":7.6,"s":1,"e":3},{"r":7.2,"s":1,"e":12},{"r":7.2,"s":1,"e":5},{"r":7.0,"s":1,"e":4},{"r":6.6,"s":1,"e":6}],"tt2623000":[{"r":6.4,"s":1,"e":1},{"r":5.4,"s":1,"e":2}],"tt2622978":[{"r":7.5,"s":1,"e":6},{"r":7.4,"s":1,"e":9},{"r":7.3,"s":1,"e":11},{"r":7.2,"s":1,"e":7},{"r":7.0,"s":1,"e":1}],"tt26255952":[{"r":7.0,"s":1,"e":4},{"r":6.9,"s":1,"e":3},{"r":6.6,"s":1,"e":2},{"r":6.1,"s":1,"e":1}],"tt2622974":[{"r":7.7,"s":1,"e":12},{"r":7.5,"s":1,"e":11},{"r":7.3,"s":1,"e":2},{"r":7.1,"s":1,"e":1},{"r":7.0,"s":1,"e":3}],"tt26228190":[{"r":9.4,"s":1,"e":14},{"r":9.2,"s":1,"e":4},{"r":9.1,"s":1,"e":7},{"r":9.1,"s":1,"e":13},{"r":9.0,"s":1,"e":17}],"tt26257058":[{"r":7.6,"s":1,"e":1},{"r":7.4,"s":1,"e":2},{"r":7.2,"s":1,"e":3}],"tt26225376":[{"r":4.3,"s":1,"e":1}],"tt26250170":[{"r":8.7,"s":1,"e":7},{"r":8.5,"s":1,"e":6},{"r":8.2,"s":1,"e":8},{"r":7.8,"s":1,"e":2},{"r":7.7,"s":1,"e":1}],"tt26229950":[{"r":8.3,"s":1,"e":1},{"r":7.7,"s":1,"e":2}],"tt2628232":[{"r":9.1,"s":3,"e":4},{"r":9.0,"s":2,"e":3},{"r":8.9,"s":2,"e":10},{"r":8.7,"s":1,"e":7},{"r":8.7,"s":2,"e":9}],"tt2624970":[{"r":7.4,"s":1,"e":2}],"tt26231794":[{"r":8.3,"s":1,"e":1},{"r":8.3,"s":1,"e":3},{"r":7.7,"s":1,"e":2}],"tt26296671":[{"r":6.2,"s":1,"e":2},{"r":5.8,"s":1,"e":1}],"tt26227818":[{"r":8.5,"s":1,"e":6},{"r":8.2,"s":1,"e":4},{"r":8.1,"s":1,"e":1},{"r":8.1,"s":1,"e":7},{"r":8.1,"s":1,"e":8}],"tt26256450":[{"r":6.3,"s":1,"e":1},{"r":6.3,"s":1,"e":3},{"r":5.8,"s":1,"e":2},{"r":5.8,"s":1,"e":4}],"tt26259966":[{"r":7.5,"s":1,"e":1}],"tt2629496":[{"r":9.0,"s":1,"e":3},{"r":9.0,"s":1,"e":4},{"r":9.0,"s":1,"e":5},{"r":8.9,"s":1,"e":2},{"r":8.9,"s":1,"e":6}],"tt2623064":[{"r":9.1,"s":1,"e":15},{"r":8.5,"s":1,"e":3},{"r":8.3,"s":1,"e":14},{"r":8.3,"s":1,"e":13},{"r":8.3,"s":1,"e":12}],"tt2624210":[{"r":6.2,"s":1,"e":4}],"tt26229000":[{"r":8.3,"s":1,"e":3},{"r":8.2,"s":1,"e":1},{"r":8.1,"s":1,"e":4},{"r":7.7,"s":1,"e":2},{"r":7.7,"s":1,"e":5}],"tt26218056":[{"r":10.0,"s":1,"e":1}],"tt2623042":[{"r":7.6,"s":1,"e":6},{"r":7.6,"s":1,"e":11},{"r":7.6,"s":1,"e":13},{"r":7.4,"s":1,"e":10},{"r":7.4,"s":1,"e":8}],"tt2621446":[{"r":7.0,"s":2,"e":1},{"r":5.8,"s":1,"e":1}],"tt2624154":[{"r":8.4,"s":1,"e":11},{"r":8.4,"s":1,"e":5},{"r":8.2,"s":1,"e":3},{"r":8.2,"s":1,"e":6},{"r":8.0,"s":1,"e":12}]}