{"tt3697842":[{"r":7.9,"s":11,"e":83},{"r":7.7,"s":11,"e":85},{"r":7.6,"s":11,"e":78},{"r":7.5,"s":4,"e":1},{"r":7.5,"s":11,"e":84}],"tt3694654":[{"r":8.8,"s":2,"e":9},{"r":8.1,"s":1,"e":3},{"r":8.0,"s":1,"e":1},{"r":8.0,"s":1,"e":2},{"r":8.0,"s":1,"e":7}],"tt3697996":[{"r":9.5,"s":3,"e":1},{"r":9.1,"s":1,"e":3},{"r":9.1,"s":3,"e":5},{"r":9.0,"s":1,"e":4},{"r":9.0,"s":4,"e":1}],"tt3696480":[{"r":8.7,"s":1,"e":3},{"r":8.6,"s":2,"e":1},{"r":8.6,"s":2,"e":3},{"r":8.6,"s":2,"e":4},{"r":8.6,"s":2,"e":5}],"tt36986796":[{"r":8.3,"s":1,"e":1}],"tt36985405":[{"r":6.8,"s":1,"e":1}],"tt36910434":[{"r":7.8,"s":1,"e":1},{"r":7.3,"s":1,"e":3},{"r":7.1,"s":1,"e":5},{"r":7.0,"s":1,"e":2},{"r":7.0,"s":1,"e":4}],"tt36912922":[{"r":8.7,"s":1,"e":6},{"r":8.5,"s":1,"e":4},{"r":8.4,"s":1,"e":10},{"r":8.4,"s":1,"e":7},{"r":8.4,"s":1,"e":11}],"tt36912840":[{"r":9.0,"s":1,"e":1},{"r":8.7,"s":1,"e":6},{"r":8.7,"s":1,"e":7},{"r":8.6,"s":1,"e":3},{"r":8.5,"s":1,"e":4}],"tt36922028":[{"r":6.0,"s":1,"e":1},{"r":5.6,"s":1,"e":2},{"r":5.4,"s":1,"e":3},{"r":4.6,"s":1,"e":4}],"tt36925946":[{"r":8.9,"s":1,"e":1},{"r":8.7,"s":1,"e":12},{"r":8.6,"s":1,"e":8},{"r":8.5,"s":1,"e":11},{"r":8.4,"s":1,"e":18}],"tt36919952":[{"r":8.1,"s":1,"e":7},{"r":7.8,"s":1,"e":2},{"r":7.7,"s":1,"e":1},{"r":7.7,"s":1,"e":3},{"r":7.7,"s":1,"e":4}],"tt36933506":[{"r":8.3,"s":1,"e":8},{"r":8.0,"s":1,"e":10},{"r":7.9,"s":1,"e":1},{"r":7.9,"s":1,"e":6},{"r":7.6,"s":1,"e":4}],"tt36933797":[{"r":7.6,"s":1,"e":1}],"tt36933775":[{"r":6.1,"s":1,"e":1}],"tt36912546":[{"r":8.9,"s":1,"e":2},{"r":8.7,"s":1,"e":10},{"r":8.6,"s":1,"e":4},{"r":8.6,"s":1,"e":6},{"r":8.6,"s":1,"e":7}],"tt36917531":[{"r":7.8,"s":1,"e":3},{"r":6.8,"s":1,"e":2}],"tt36943043":[{"r":7.5,"s":1,"e":1},{"r":7.4,"s":1,"e":2}],"tt36941799":[{"r":9.7,"s":9,"e":5},{"r":9.6,"s":3,"e":4},{"r":9.5,"s":5,"e":3},{"r":9.5,"s":5,"e":1},{"r":9.5,"s":9,"e":3}],"tt36951033":[{"r":8.0,"s":1,"e":2},{"r":8.0,"s":1,"e":7},{"r":7.9,"s":1,"e":10},{"r":7.8,"s":1,"e":3},{"r":7.6,"s":1,"e":4}],"tt36926665":[{"r":6.6,"s":1,"e":2},{"r":6.5,"s":1,"e":3},{"r":6.3,"s":1,"e":1}],"tt36948226":[{"r":4.8,"s":1,"e":1}],"tt36953849":[{"r":7.1,"s":1,"e":6},{"r":6.8,"s":1,"e":4},{"r":6.7,"s":1,"e":5},{"r":6.6,"s":1,"e":2},{"r":6.4,"s":1,"e":3}],"tt36958827":[{"r":6.9,"s":1,"e":2},{"r":6.6,"s":1,"e":1},{"r":6.0,"s":1,"e":3}],"tt36958273":[{"r":8.1,"s":1,"e":2},{"r":8.0,"s":1,"e":1},{"r":8.0,"s":1,"e":9},{"r":7.8,"s":1,"e":4},{"r":7.0,"s":1,"e":3}],"tt36958075":[{"r":9.4,"s":1,"e":1}],"tt36964956":[{"r":7.4,"s":1,"e":3},{"r":7.4,"s":1,"e":6},{"r":7.0,"s":1,"e":4},{"r":6.9,"s":1,"e":2},{"r":6.9,"s":1,"e":5}],"tt36966597":[{"r":8.2,"s":1,"e":4},{"r":7.9,"s":1,"e":5},{"r":7.6,"s":1,"e":10},{"r":7.5,"s":1,"e":2},{"r":7.4,"s":1,"e":6}],"tt36966608":[{"r":7.6,"s":1,"e":2},{"r":7.2,"s":1,"e":3},{"r":6.7,"s":1,"e":10},{"r":6.4,"s":1,"e":1},{"r":6.4,"s":1,"e":7}],"tt3691294":[{"r":8.2,"s":1,"e":2},{"r":7.0,"s":1,"e":1},{"r":6.8,"s":1,"e":3}],"tt36980623":[{"r":10.0,"s":1,"e":2},{"r":10.0,"s":1,"e":3},{"r":10.0,"s":1,"e":4},{"r":10.0,"s":1,"e":5},{"r":10.0,"s":1,"e":6}],"tt36983163":[{"r":8.0,"s":1,"e":2},{"r":7.9,"s":1,"e":1}],"tt36932951":[{"r":8.8,"s":1,"e":1}],"tt36984001":[{"r":7.6,"s":1,"e":6},{"r":7.3,"s":1,"e":5},{"r":6.8,"s":1,"e":1},{"r":6.8,"s":1,"e":4},{"r":6.6,"s":1,"e":2}],"tt36985473":[{"r":9.4,"s":2,"e":20},{"r":9.1,"s":2,"e":9},{"r":9.0,"s":1,"e":18},{"r":9.0,"s":2,"e":14},{"r":8.9,"s":2,"e":7}],"tt36985714":[{"r":7.6,"s":1,"e":2},{"r":7.4,"s":1,"e":1},{"r":7.2,"s":1,"e":3}],"tt36986366":[{"r":7.0,"s":1,"e":1},{"r":6.5,"s":1,"e":2}],"tt36988423":[{"r":5.0,"s":1,"e":1}],"tt36988358":[{"r":9.6,"s":1,"e":5},{"r":9.5,"s":1,"e":1},{"r":9.5,"s":1,"e":2},{"r":9.4,"s":1,"e":4},{"r":9.3,"s":1,"e":6}],"tt3690362":[{"r":8.0,"s":1,"e":2},{"r":8.0,"s":1,"e":3},{"r":7.8,"s":1,"e":1},{"r":7.8,"s":1,"e":4}],"tt36957464":[{"r":8.3,"s":1,"e":2},{"r":7.2,"s":1,"e":1}],"tt36955463":[{"r":9.0,"s":1,"e":3},{"r":9.0,"s":1,"e":6},{"r":8.8,"s":1,"e":2},{"r":8.8,"s":1,"e":5},{"r":8.7,"s":1,"e":4}],"tt36981721":[{"r":7.2,"s":1,"e":2},{"r":6.8,"s":1,"e":10},{"r":6.5,"s":1,"e":8},{"r":6.5,"s":1,"e":9},{"r":6.4,"s":1,"e":3}],"tt36958533":[{"r":6.6,"s":1,"e":1},{"r":6.3,"s":1,"e":2},{"r":6.3,"s":1,"e":3},{"r":5.3,"s":1,"e":4}],"tt3697290":[{"r":2.7,"s":2,"e":5}],"tt36998986":[{"r":8.5,"s":1,"e":2},{"r":8.5,"s":1,"e":3},{"r":8.5,"s":1,"e":4},{"r":8.5,"s":1,"e":5},{"r":8.3,"s":1,"e":1}],"tt3692970":[{"r":8.3,"s":1,"e":4},{"r":7.9,"s":1,"e":2},{"r":7.5,"s":1,"e":3},{"r":7.4,"s":1,"e":1},{"r":6.1,"s":1,"e":5}],"tt36984460":[{"r":10.0,"s":1,"e":13},{"r":10.0,"s":1,"e":16},{"r":10.0,"s":1,"e":18},{"r":10.0,"s":1,"e":17},{"r":10.0,"s":1,"e":19}],"tt36933520":[{"r":7.8,"s":1,"e":10},{"r":7.5,"s":1,"e":7},{"r":7.4,"s":1,"e":6},{"r":7.4,"s":1,"e":9},{"r":7.3,"s":1,"e":2}],"tt36988223":[{"r":7.6,"s":1,"e":3},{"r":7.3,"s":1,"e":1},{"r":7.3,"s":1,"e":2},{"r":6.9,"s":1,"e":4}],"tt3691462":[{"r":8.3,"s":2,"e":10},{"r":8.1,"s":4,"e":6},{"r":8.1,"s":3,"e":8},{"r":8.0,"s":1,"e":2},{"r":8.0,"s":3,"e":13}],"tt3690706":[{"r":8.2,"s":1,"e":5},{"r":8.1,"s":1,"e":3},{"r":7.8,"s":1,"e":4},{"r":7.6,"s":1,"e":6},{"r":7.5,"s":1,"e":1}],"tt36968329":[{"r":7.1,"s":1,"e":2},{"r":6.9,"s":1,"e":5},{"r":6.8,"s":1,"e":3},{"r":6.7,"s":1,"e":6},{"r":6.5,"s":1,"e":1}],"tt3692198":[{"r":8.0,"s":2,"e":5},{"r":7.7,"s":1,"e":11},{"r":7.5,"s":1,"e":12},{"r":7.4,"s":1,"e":1},{"r":7.3,"s":2,"e":3}],"tt36909877":[{"r":6.3,"s":1,"e":1},{"r":6.2,"s":1,"e":2},{"r":6.2,"s":1,"e":7},{"r":6.1,"s":1,"e":3},{"r":6.0,"s":1,"e":4}],"tt36933578":[{"r":8.1,"s":1,"e":6},{"r":7.9,"s":1,"e":7},{"r":7.7,"s":1,"e":5},{"r":7.3,"s":1,"e":2},{"r":7.2,"s":1,"e":3}],"tt36988220":[{"r":8.1,"s":1,"e":10},{"r":7.7,"s":1,"e":12},{"r":7.6,"s":1,"e":2},{"r":7.5,"s":1,"e":6},{"r":7.4,"s":1,"e":1}],"tt36987898":[{"r":6.9,"s":1,"e":9},{"r":5.8,"s":1,"e":10},{"r":5.7,"s":1,"e":4},{"r":5.5,"s":1,"e":1},{"r":5.3,"s":1,"e":8}],"tt36998336":[{"r":8.1,"s":1,"e":5},{"r":8.0,"s":1,"e":4},{"r":8.0,"s":1,"e":11},{"r":7.9,"s":1,"e":12},{"r":7.8,"s":1,"e":1}],"tt36957172":[{"r":7.6,"s":1,"e":5},{"r":7.4,"s":1,"e":4},{"r":7.4,"s":1,"e":6},{"r":6.2,"s":1,"e":1}],"tt36955264":[{"r":7.3,"s":1,"e":8},{"r":6.9,"s":1,"e":7},{"r":6.8,"s":1,"e":5},{"r":6.8,"s":1,"e":6},{"r":6.7,"s":1,"e":3}],"tt36958358":[{"r":8.4,"s":1,"e":3},{"r":8.3,"s":1,"e":2},{"r":7.6,"s":1,"e":1},{"r":7.3,"s":1,"e":4}],"tt36937533":[{"r":9.3,"s":1,"e":3},{"r":9.1,"s":1,"e":6},{"r":9.0,"s":1,"e":5},{"r":8.7,"s":1,"e":4},{"r":8.3,"s":1,"e":1}],"tt36987681":[{"r":8.3,"s":1,"e":5},{"r":8.2,"s":1,"e":6},{"r":8.2,"s":1,"e":7},{"r":8.0,"s":1,"e":2},{"r":8.0,"s":1,"e":11}],"tt36998181":[{"r":9.2,"s":1,"e":8},{"r":9.1,"s":1,"e":7},{"r":9.1,"s":1,"e":9},{"r":9.0,"s":1,"e":3},{"r":9.0,"s":1,"e":5}],"tt36941251":[{"r":8.0,"s":1,"e":7},{"r":7.7,"s":1,"e":4},{"r":7.6,"s":1,"e":5},{"r":7.6,"s":1,"e":8},{"r":7.5,"s":1,"e":2}],"tt3696720":[{"r":7.3,"s":1,"e":1},{"r":7.3,"s":1,"e":2},{"r":7.3,"s":1,"e":3}],"tt36935784":[{"r":8.1,"s":1,"e":4},{"r":7.9,"s":1,"e":1},{"r":7.9,"s":1,"e":3},{"r":7.8,"s":1,"e":2},{"r":7.8,"s":1,"e":5}],"tt36938638":[{"r":6.9,"s":1,"e":3},{"r":6.7,"s":1,"e":1},{"r":6.4,"s":1,"e":2},{"r":6.2,"s":1,"e":5},{"r":6.2,"s":1,"e":4}],"tt36956617":[{"r":7.9,"s":1,"e":6},{"r":7.8,"s":1,"e":1},{"r":7.8,"s":1,"e":4},{"r":7.6,"s":1,"e":5},{"r":7.6,"s":1,"e":3}],"tt3696476":[{"r":9.7,"s":2,"e":26},{"r":9.7,"s":2,"e":45},{"r":9.7,"s":3,"e":2},{"r":9.7,"s":3,"e":3},{"r":9.7,"s":3,"e":12}],"tt36957282":[{"r":7.3,"s":1,"e":8},{"r":7.2,"s":1,"e":7},{"r":6.9,"s":1,"e":3},{"r":6.8,"s":1,"e":4},{"r":6.7,"s":1,"e":6}],"tt3697872":[{"r":7.8,"s":1,"e":10},{"r":7.6,"s":1,"e":11},{"r":7.6,"s":1,"e":12},{"r":7.2,"s":1,"e":4},{"r":7.2,"s":1,"e":3}],"tt36985130":[{"r":8.4,"s":1,"e":2},{"r":7.6,"s":1,"e":1}],"tt3692064":[{"r":6.5,"s":1,"e":1},{"r":6.3,"s":1,"e":8},{"r":6.3,"s":1,"e":9},{"r":6.2,"s":1,"e":2},{"r":6.2,"s":1,"e":11}],"tt3694548":[{"r":7.7,"s":1,"e":2}],"tt3693428":[{"r":8.3,"s":1,"e":20},{"r":8.0,"s":1,"e":4},{"r":7.8,"s":1,"e":1},{"r":7.8,"s":1,"e":5},{"r":7.8,"s":1,"e":8}],"tt3693414":[{"r":8.7,"s":1,"e":18},{"r":8.4,"s":1,"e":1},{"r":8.3,"s":1,"e":19},{"r":8.2,"s":1,"e":3},{"r":8.2,"s":1,"e":10}],"tt3699708":[{"r":7.1,"s":1,"e":1}],"tt3691530":[{"r":8.3,"s":1,"e":1}],"tt3696748":[{"r":6.8,"s":1,"e":2},{"r":6.7,"s":1,"e":3},{"r":6.5,"s":1,"e":1},{"r":6.2,"s":1,"e":4},{"r":5.9,"s":1,"e":5}],"tt3692292":[{"r":5.8,"s":1,"e":1},{"r":5.3,"s":1,"e":3},{"r":5.0,"s":1,"e":4},{"r":4.8,"s":1,"e":12},{"r":4.7,"s":1,"e":2}]}