{"tt5757090":[{"r":6.4,"s":1,"e":1}],"tt5753856":[{"r":9.6,"s":3,"e":8},{"r":9.5,"s":2,"e":6},{"r":9.4,"s":3,"e":7},{"r":9.4,"s":2,"e":8},{"r":9.4,"s":2,"e":4}],"tt5754602":[{"r":8.7,"s":1,"e":6},{"r":8.7,"s":2,"e":7},{"r":8.5,"s":1,"e":5},{"r":8.5,"s":3,"e":4},{"r":8.5,"s":3,"e":6}],"tt5759360":[{"r":8.8,"s":1,"e":2},{"r":8.7,"s":1,"e":3},{"r":8.7,"s":1,"e":4},{"r":8.5,"s":1,"e":1}],"tt5754262":[{"r":9.4,"s":1,"e":2}],"tt5753374":[{"r":7.7,"s":1,"e":1},{"r":7.5,"s":1,"e":11},{"r":7.2,"s":1,"e":7},{"r":7.2,"s":1,"e":5},{"r":7.2,"s":1,"e":9}],"tt5759616":[{"r":7.0,"s":1,"e":3},{"r":6.8,"s":1,"e":1},{"r":6.4,"s":1,"e":2}],"tt5752856":[{"r":7.2,"s":1,"e":1},{"r":7.2,"s":1,"e":3},{"r":7.1,"s":1,"e":2}],"tt5758982":[{"r":7.7,"s":1,"e":1}],"tt5750932":[{"r":8.9,"s":1,"e":2},{"r":8.7,"s":1,"e":1}],"tt5759492":[{"r":6.0,"s":1,"e":18},{"r":2.1,"s":1,"e":46}],"tt5759474":[{"r":4.5,"s":1,"e":28}],"tt5754594":[{"r":3.3,"s":1,"e":1},{"r":3.3,"s":1,"e":2},{"r":2.4,"s":1,"e":3},{"r":2.1,"s":1,"e":4}],"tt5750420":[{"r":7.5,"s":1,"e":6},{"r":7.2,"s":1,"e":1},{"r":6.9,"s":1,"e":2},{"r":6.8,"s":1,"e":7},{"r":6.8,"s":1,"e":5}],"tt5759196":[{"r":8.0,"s":3,"e":4},{"r":7.9,"s":1,"e":13},{"r":7.5,"s":2,"e":2},{"r":7.5,"s":4,"e":1},{"r":7.3,"s":2,"e":1}],"tt5759648":[{"r":8.1,"s":1,"e":9},{"r":8.0,"s":1,"e":7},{"r":7.8,"s":1,"e":8},{"r":7.8,"s":1,"e":5},{"r":7.7,"s":1,"e":6}],"tt5754620":[{"r":8.2,"s":1,"e":6},{"r":8.0,"s":1,"e":1},{"r":8.0,"s":2,"e":3},{"r":8.0,"s":2,"e":4},{"r":8.0,"s":2,"e":7}],"tt5753664":[{"r":8.2,"s":1,"e":1}]}