{"tt5905202":[{"r":8.0,"s":3,"e":1},{"r":8.0,"s":2,"e":5},{"r":8.0,"s":3,"e":6},{"r":7.8,"s":1,"e":3},{"r":7.8,"s":2,"e":3}],"tt5905038":[{"r":8.9,"s":1,"e":7},{"r":8.8,"s":1,"e":10},{"r":8.8,"s":2,"e":7},{"r":8.7,"s":3,"e":8},{"r":8.7,"s":3,"e":6}],"tt5905354":[{"r":7.7,"s":3,"e":5},{"r":7.6,"s":3,"e":6},{"r":7.4,"s":1,"e":6},{"r":7.4,"s":2,"e":5},{"r":7.4,"s":3,"e":1}],"tt5907796":[{"r":9.7,"s":7,"e":11},{"r":9.2,"s":7,"e":12},{"r":8.8,"s":7,"e":1},{"r":8.8,"s":7,"e":2},{"r":8.8,"s":7,"e":10}],"tt5906126":[{"r":9.4,"s":1,"e":2},{"r":9.2,"s":2,"e":1},{"r":9.1,"s":1,"e":1},{"r":9.1,"s":1,"e":6},{"r":9.1,"s":2,"e":5}],"tt5902204":[{"r":8.7,"s":1,"e":6},{"r":8.6,"s":1,"e":5},{"r":8.4,"s":1,"e":1},{"r":8.4,"s":1,"e":2},{"r":8.4,"s":1,"e":3}],"tt5905148":[{"r":8.2,"s":1,"e":4},{"r":7.9,"s":1,"e":1},{"r":7.8,"s":1,"e":2},{"r":7.6,"s":1,"e":3},{"r":7.4,"s":1,"e":5}],"tt5903724":[{"r":8.8,"s":1,"e":4},{"r":8.2,"s":1,"e":10},{"r":8.0,"s":1,"e":6},{"r":7.8,"s":1,"e":1},{"r":7.8,"s":2,"e":4}],"tt5900898":[{"r":9.2,"s":9,"e":9},{"r":8.8,"s":7,"e":7},{"r":8.8,"s":4,"e":37},{"r":8.4,"s":7,"e":21},{"r":8.2,"s":2,"e":9}],"tt5908292":[{"r":7.6,"s":1,"e":2},{"r":7.3,"s":1,"e":8},{"r":6.4,"s":1,"e":5},{"r":6.3,"s":1,"e":1},{"r":6.3,"s":1,"e":4}],"tt5904172":[{"r":7.8,"s":2,"e":3},{"r":7.6,"s":2,"e":8},{"r":7.5,"s":2,"e":5},{"r":7.4,"s":2,"e":2},{"r":7.4,"s":2,"e":4}],"tt5907228":[{"r":8.1,"s":1,"e":4},{"r":8.0,"s":1,"e":1},{"r":8.0,"s":1,"e":2},{"r":7.9,"s":1,"e":3}],"tt5906924":[{"r":8.1,"s":1,"e":4},{"r":8.0,"s":1,"e":2},{"r":7.7,"s":1,"e":5},{"r":7.7,"s":1,"e":6},{"r":7.5,"s":1,"e":3}],"tt5909184":[{"r":7.2,"s":1,"e":4},{"r":7.2,"s":1,"e":5},{"r":7.2,"s":1,"e":6},{"r":7.1,"s":1,"e":1},{"r":7.0,"s":1,"e":2}],"tt5909786":[{"r":8.8,"s":1,"e":1}],"tt5901890":[{"r":8.5,"s":1,"e":5},{"r":8.0,"s":1,"e":10},{"r":7.6,"s":1,"e":8},{"r":7.5,"s":1,"e":4},{"r":7.2,"s":1,"e":9}],"tt5900164":[{"r":6.9,"s":1,"e":1},{"r":6.8,"s":1,"e":2},{"r":6.7,"s":1,"e":3},{"r":6.3,"s":1,"e":4},{"r":6.2,"s":2,"e":1}],"tt5908376":[{"r":9.2,"s":1,"e":1}],"tt5905350":[{"r":9.0,"s":1,"e":13},{"r":9.0,"s":1,"e":9},{"r":8.7,"s":1,"e":8},{"r":8.7,"s":1,"e":12},{"r":8.2,"s":1,"e":6}],"tt5908004":[{"r":9.7,"s":1,"e":1}],"tt5903288":[{"r":8.2,"s":1,"e":4},{"r":7.7,"s":1,"e":2},{"r":7.3,"s":1,"e":3},{"r":7.0,"s":1,"e":1}],"tt5905508":[{"r":6.7,"s":1,"e":3},{"r":6.7,"s":1,"e":1},{"r":6.5,"s":1,"e":2}],"tt5903040":[{"r":8.6,"s":1,"e":11},{"r":8.1,"s":1,"e":5},{"r":7.8,"s":1,"e":4},{"r":7.7,"s":1,"e":9},{"r":7.6,"s":1,"e":2}],"tt5900600":[{"r":8.2,"s":1,"e":6},{"r":8.1,"s":1,"e":2},{"r":8.1,"s":1,"e":3},{"r":7.8,"s":1,"e":1},{"r":7.8,"s":1,"e":5}],"tt5905344":[{"r":7.4,"s":1,"e":4},{"r":7.2,"s":1,"e":3},{"r":7.1,"s":1,"e":2},{"r":7.0,"s":1,"e":13},{"r":7.0,"s":1,"e":6}],"tt5904498":[{"r":8.9,"s":1,"e":1}],"tt5900618":[{"r":8.2,"s":2,"e":1}],"tt5905194":[{"r":6.8,"s":1,"e":2},{"r":6.8,"s":1,"e":4},{"r":6.7,"s":1,"e":1},{"r":6.5,"s":1,"e":3},{"r":6.0,"s":1,"e":5}],"tt5909930":[{"r":7.8,"s":1,"e":3},{"r":7.6,"s":1,"e":2},{"r":7.0,"s":1,"e":1}]}