{"tt8509962":[{"r":6.1,"s":1,"e":1}],"tt8500760":[{"r":9.7,"s":2,"e":5},{"r":9.3,"s":1,"e":5},{"r":9.2,"s":2,"e":1},{"r":8.9,"s":2,"e":4},{"r":8.8,"s":2,"e":3}],"tt8503572":[{"r":7.6,"s":1,"e":2},{"r":7.3,"s":1,"e":4},{"r":7.1,"s":1,"e":1},{"r":7.1,"s":1,"e":6},{"r":7.1,"s":1,"e":10}],"tt8502324":[{"r":7.6,"s":1,"e":1},{"r":7.6,"s":2,"e":4},{"r":7.5,"s":1,"e":3},{"r":7.5,"s":1,"e":5},{"r":7.4,"s":1,"e":2}],"tt8509922":[{"r":8.5,"s":1,"e":8},{"r":8.2,"s":1,"e":6},{"r":7.9,"s":1,"e":4},{"r":7.9,"s":1,"e":5},{"r":7.8,"s":1,"e":3}],"tt8501976":[{"r":4.6,"s":1,"e":1}],"tt8500086":[{"r":7.4,"s":1,"e":7},{"r":7.3,"s":1,"e":6},{"r":7.2,"s":1,"e":1},{"r":7.2,"s":1,"e":2},{"r":7.2,"s":1,"e":3}],"tt8507402":[{"r":8.4,"s":1,"e":6},{"r":8.3,"s":1,"e":5},{"r":8.1,"s":1,"e":1},{"r":7.8,"s":1,"e":2},{"r":7.8,"s":1,"e":10}],"tt8504990":[{"r":7.2,"s":1,"e":3},{"r":6.5,"s":1,"e":1}],"tt8501736":[{"r":9.3,"s":2,"e":3}],"tt8502560":[{"r":9.0,"s":1,"e":3},{"r":8.6,"s":1,"e":5},{"r":8.3,"s":1,"e":2},{"r":8.2,"s":1,"e":4},{"r":8.0,"s":1,"e":7}],"tt8503628":[{"r":7.7,"s":1,"e":5},{"r":7.4,"s":1,"e":13},{"r":7.2,"s":1,"e":12},{"r":7.1,"s":1,"e":7},{"r":6.9,"s":1,"e":11}]}