{"tt9915686":[{"r":7.2,"s":1,"e":1}],"tt9915144":[{"r":9.8,"s":1,"e":4},{"r":9.6,"s":1,"e":3},{"r":9.4,"s":1,"e":1},{"r":9.4,"s":1,"e":5},{"r":9.4,"s":1,"e":2}],"tt9916380":[{"r":9.9,"s":1,"e":3},{"r":9.9,"s":1,"e":4},{"r":9.9,"s":1,"e":5},{"r":9.9,"s":1,"e":9},{"r":9.5,"s":1,"e":1}],"tt9910728":[{"r":7.3,"s":1,"e":1},{"r":7.2,"s":1,"e":2},{"r":7.2,"s":1,"e":5},{"r":7.2,"s":1,"e":4},{"r":7.1,"s":1,"e":3}],"tt9914546":[{"r":9.6,"s":1,"e":2},{"r":7.1,"s":1,"e":1}],"tt9915822":[{"r":9.3,"s":1,"e":1}],"tt9916128":[{"r":9.5,"s":1,"e":1},{"r":9.1,"s":1,"e":7},{"r":9.1,"s":1,"e":6},{"r":8.7,"s":1,"e":3},{"r":8.7,"s":1,"e":4}],"tt9910672":[{"r":8.0,"s":1,"e":5},{"r":7.6,"s":1,"e":1},{"r":7.2,"s":1,"e":4},{"r":7.0,"s":1,"e":2},{"r":6.8,"s":1,"e":3}],"tt9914700":[{"r":8.2,"s":1,"e":1},{"r":7.8,"s":1,"e":4}]}